gparms/__init__.py
gparms/gparms.py
gparms-0.0.8.dist-info/METADATA
gparms-0.0.8.dist-info/WHEEL
gparms-0.0.8.dist-info/entry_points.txt
gparms-0.0.8.dist-info/top_level.txt
gparms-0.0.8.dist-info/RECORD
