Metadata-Version: 2.1
Name: gparms
Version: 0.0.8
Summary: Get URL Parameters
Author: Shelled
License: UNKNOWN
Keywords: python,bug bounty,pentesting,url
Platform: UNKNOWN
Classifier: Development Status :: 1 - Planning
Classifier: Intended Audience :: Developers
Classifier: Programming Language :: Python :: 3
Classifier: Operating System :: Unix
Classifier: Operating System :: MacOS :: MacOS X
Classifier: Operating System :: Microsoft :: Windows
